jump_reward_inference/__init__.py
jump_reward_inference/inference.py
jump_reward_inference/joint_tracker.py
jump_reward_inference/state_space_1D.py
jump_reward_inference-0.0.8.dist-info/LICENSE
jump_reward_inference-0.0.8.dist-info/METADATA
jump_reward_inference-0.0.8.dist-info/WHEEL
jump_reward_inference-0.0.8.dist-info/top_level.txt
jump_reward_inference-0.0.8.dist-info/RECORD
